[
  {
    "ContainingType": "EmployeeManagement.WebAPI.Controllers.AuthController",
    "Method": "Login",
    "RelativePath": "api/auth/login",
    "HttpMethod": "POST",
    "IsController": true,
    "Order": 0,
    "Parameters": [
      {
        "Name": "request",
        "Type": "EmployeeManagement.Application.DTOs.Request.Auth.LoginRequest",
        "IsRequired": true
      }
    ],
    "ReturnTypes": []
  },
  {
    "ContainingType": "EmployeeManagement.WebAPI.Controllers.AuthController",
    "Method": "Logout",
    "RelativePath": "api/auth/logout",
    "HttpMethod": "POST",
    "IsController": true,
    "Order": 0,
    "Parameters": [],
    "ReturnTypes": []
  },
  {
    "ContainingType": "EmployeeManagement.WebAPI.Controllers.DepartmentController",
    "Method": "GetAll",
    "RelativePath": "api/departments",
    "HttpMethod": "GET",
    "IsController": true,
    "Order": 0,
    "Parameters": [],
    "ReturnTypes": []
  },
  {
    "ContainingType": "EmployeeManagement.WebAPI.Controllers.DepartmentController",
    "Method": "Create",
    "RelativePath": "api/departments",
    "HttpMethod": "POST",
    "IsController": true,
    "Order": 0,
    "Parameters": [
      {
        "Name": "request",
        "Type": "EmployeeManagement.Application.DTOs.Request.Department.CreateDepartmentRequest",
        "IsRequired": true
      }
    ],
    "ReturnTypes": []
  },
  {
    "ContainingType": "EmployeeManagement.WebAPI.Controllers.DepartmentController",
    "Method": "GetById",
    "RelativePath": "api/departments/{id}",
    "HttpMethod": "GET",
    "IsController": true,
    "Order": 0,
    "Parameters": [
      {
        "Name": "id",
        "Type": "System.Guid",
        "IsRequired": true
      }
    ],
    "ReturnTypes": []
  },
  {
    "ContainingType": "EmployeeManagement.WebAPI.Controllers.DepartmentController",
    "Method": "Update",
    "RelativePath": "api/departments/{id}",
    "HttpMethod": "PUT",
    "IsController": true,
    "Order": 0,
    "Parameters": [
      {
        "Name": "id",
        "Type": "System.Guid",
        "IsRequired": true
      },
      {
        "Name": "request",
        "Type": "EmployeeManagement.Application.DTOs.Request.Department.UpdateDepartmentRequest",
        "IsRequired": true
      }
    ],
    "ReturnTypes": []
  },
  {
    "ContainingType": "EmployeeManagement.WebAPI.Controllers.DepartmentController",
    "Method": "Delete",
    "RelativePath": "api/departments/{id}",
    "HttpMethod": "DELETE",
    "IsController": true,
    "Order": 0,
    "Parameters": [
      {
        "Name": "id",
        "Type": "System.Guid",
        "IsRequired": true
      }
    ],
    "ReturnTypes": []
  },
  {
    "ContainingType": "EmployeeManagement.WebAPI.Controllers.DesignationController",
    "Method": "GetAll",
    "RelativePath": "api/designations",
    "HttpMethod": "GET",
    "IsController": true,
    "Order": 0,
    "Parameters": [],
    "ReturnTypes": []
  },
  {
    "ContainingType": "EmployeeManagement.WebAPI.Controllers.DesignationController",
    "Method": "Create",
    "RelativePath": "api/designations",
    "HttpMethod": "POST",
    "IsController": true,
    "Order": 0,
    "Parameters": [
      {
        "Name": "request",
        "Type": "EmployeeManagement.Application.DTOs.Request.Designation.CreateDesignationRequest",
        "IsRequired": true
      }
    ],
    "ReturnTypes": []
  },
  {
    "ContainingType": "EmployeeManagement.WebAPI.Controllers.DesignationController",
    "Method": "GetById",
    "RelativePath": "api/designations/{id}",
    "HttpMethod": "GET",
    "IsController": true,
    "Order": 0,
    "Parameters": [
      {
        "Name": "id",
        "Type": "System.Guid",
        "IsRequired": true
      }
    ],
    "ReturnTypes": []
  },
  {
    "ContainingType": "EmployeeManagement.WebAPI.Controllers.DesignationController",
    "Method": "Update",
    "RelativePath": "api/designations/{id}",
    "HttpMethod": "PUT",
    "IsController": true,
    "Order": 0,
    "Parameters": [
      {
        "Name": "id",
        "Type": "System.Guid",
        "IsRequired": true
      },
      {
        "Name": "request",
        "Type": "EmployeeManagement.Application.DTOs.Request.Designation.UpdateDesignationRequest",
        "IsRequired": true
      }
    ],
    "ReturnTypes": []
  },
  {
    "ContainingType": "EmployeeManagement.WebAPI.Controllers.DesignationController",
    "Method": "Delete",
    "RelativePath": "api/designations/{id}",
    "HttpMethod": "DELETE",
    "IsController": true,
    "Order": 0,
    "Parameters": [
      {
        "Name": "id",
        "Type": "System.Guid",
        "IsRequired": true
      }
    ],
    "ReturnTypes": []
  },
  {
    "ContainingType": "EmployeeManagement.WebAPI.Controllers.EmployeeController",
    "Method": "GetAll",
    "RelativePath": "api/employees",
    "HttpMethod": "GET",
    "IsController": true,
    "Order": 0,
    "Parameters": [],
    "ReturnTypes": []
  },
  {
    "ContainingType": "EmployeeManagement.WebAPI.Controllers.EmployeeController",
    "Method": "Create",
    "RelativePath": "api/employees",
    "HttpMethod": "POST",
    "IsController": true,
    "Order": 0,
    "Parameters": [
      {
        "Name": "request",
        "Type": "EmployeeManagement.Application.DTOs.Request.Employee.CreateEmployeeRequest",
        "IsRequired": true
      }
    ],
    "ReturnTypes": []
  },
  {
    "ContainingType": "EmployeeManagement.WebAPI.Controllers.EmployeeController",
    "Method": "GetById",
    "RelativePath": "api/employees/{id}",
    "HttpMethod": "GET",
    "IsController": true,
    "Order": 0,
    "Parameters": [
      {
        "Name": "id",
        "Type": "System.Guid",
        "IsRequired": true
      }
    ],
    "ReturnTypes": []
  },
  {
    "ContainingType": "EmployeeManagement.WebAPI.Controllers.EmployeeController",
    "Method": "Update",
    "RelativePath": "api/employees/{id}",
    "HttpMethod": "PUT",
    "IsController": true,
    "Order": 0,
    "Parameters": [
      {
        "Name": "id",
        "Type": "System.Guid",
        "IsRequired": true
      },
      {
        "Name": "request",
        "Type": "EmployeeManagement.Application.DTOs.Request.Employee.UpdateEmployeeRequest",
        "IsRequired": true
      }
    ],
    "ReturnTypes": []
  },
  {
    "ContainingType": "EmployeeManagement.WebAPI.Controllers.EmployeeController",
    "Method": "Deactivate",
    "RelativePath": "api/employees/{id}/deactivate",
    "HttpMethod": "PATCH",
    "IsController": true,
    "Order": 0,
    "Parameters": [
      {
        "Name": "id",
        "Type": "System.Guid",
        "IsRequired": true
      }
    ],
    "ReturnTypes": []
  },
  {
    "ContainingType": "EmployeeManagement.WebAPI.Controllers.PermissionController",
    "Method": "GetAll",
    "RelativePath": "api/permissions",
    "HttpMethod": "GET",
    "IsController": true,
    "Order": 0,
    "Parameters": [],
    "ReturnTypes": []
  },
  {
    "ContainingType": "EmployeeManagement.WebAPI.Controllers.PermissionController",
    "Method": "Create",
    "RelativePath": "api/permissions",
    "HttpMethod": "POST",
    "IsController": true,
    "Order": 0,
    "Parameters": [
      {
        "Name": "request",
        "Type": "EmployeeManagement.Application.DTOs.Request.Permission.CreatePermissionRequest",
        "IsRequired": true
      }
    ],
    "ReturnTypes": []
  },
  {
    "ContainingType": "EmployeeManagement.WebAPI.Controllers.PermissionController",
    "Method": "GetById",
    "RelativePath": "api/permissions/{id}",
    "HttpMethod": "GET",
    "IsController": true,
    "Order": 0,
    "Parameters": [
      {
        "Name": "id",
        "Type": "System.Guid",
        "IsRequired": true
      }
    ],
    "ReturnTypes": []
  },
  {
    "ContainingType": "EmployeeManagement.WebAPI.Controllers.PermissionController",
    "Method": "Delete",
    "RelativePath": "api/permissions/{id}",
    "HttpMethod": "DELETE",
    "IsController": true,
    "Order": 0,
    "Parameters": [
      {
        "Name": "id",
        "Type": "System.Guid",
        "IsRequired": true
      }
    ],
    "ReturnTypes": []
  },
  {
    "ContainingType": "EmployeeManagement.WebAPI.Controllers.ReportController",
    "Method": "GetEmployeeSalaryHistory",
    "RelativePath": "api/reports/employee-salary-history/{employeeId}",
    "HttpMethod": "GET",
    "IsController": true,
    "Order": 0,
    "Parameters": [
      {
        "Name": "employeeId",
        "Type": "System.Guid",
        "IsRequired": true
      }
    ],
    "ReturnTypes": []
  },
  {
    "ContainingType": "EmployeeManagement.WebAPI.Controllers.ReportController",
    "Method": "GetMonthlySummary",
    "RelativePath": "api/reports/monthly-summary/{year}",
    "HttpMethod": "GET",
    "IsController": true,
    "Order": 0,
    "Parameters": [
      {
        "Name": "year",
        "Type": "System.Int32",
        "IsRequired": true
      }
    ],
    "ReturnTypes": []
  },
  {
    "ContainingType": "EmployeeManagement.WebAPI.Controllers.ReportController",
    "Method": "GetSalaryByDepartment",
    "RelativePath": "api/reports/salary-by-department",
    "HttpMethod": "GET",
    "IsController": true,
    "Order": 0,
    "Parameters": [],
    "ReturnTypes": []
  },
  {
    "ContainingType": "EmployeeManagement.WebAPI.Controllers.ReportController",
    "Method": "GetTotalDisbursed",
    "RelativePath": "api/reports/total-disbursed/{month}/{year}",
    "HttpMethod": "GET",
    "IsController": true,
    "Order": 0,
    "Parameters": [
      {
        "Name": "month",
        "Type": "System.Int32",
        "IsRequired": true
      },
      {
        "Name": "year",
        "Type": "System.Int32",
        "IsRequired": true
      }
    ],
    "ReturnTypes": []
  },
  {
    "ContainingType": "EmployeeManagement.WebAPI.Controllers.RoleController",
    "Method": "GetAll",
    "RelativePath": "api/roles",
    "HttpMethod": "GET",
    "IsController": true,
    "Order": 0,
    "Parameters": [],
    "ReturnTypes": []
  },
  {
    "ContainingType": "EmployeeManagement.WebAPI.Controllers.RoleController",
    "Method": "Create",
    "RelativePath": "api/roles",
    "HttpMethod": "POST",
    "IsController": true,
    "Order": 0,
    "Parameters": [
      {
        "Name": "request",
        "Type": "EmployeeManagement.Application.DTOs.Request.Role.CreateRoleRequest",
        "IsRequired": true
      }
    ],
    "ReturnTypes": []
  },
  {
    "ContainingType": "EmployeeManagement.WebAPI.Controllers.RoleController",
    "Method": "GetById",
    "RelativePath": "api/roles/{id}",
    "HttpMethod": "GET",
    "IsController": true,
    "Order": 0,
    "Parameters": [
      {
        "Name": "id",
        "Type": "System.Guid",
        "IsRequired": true
      }
    ],
    "ReturnTypes": []
  },
  {
    "ContainingType": "EmployeeManagement.WebAPI.Controllers.RoleController",
    "Method": "Update",
    "RelativePath": "api/roles/{id}",
    "HttpMethod": "PUT",
    "IsController": true,
    "Order": 0,
    "Parameters": [
      {
        "Name": "id",
        "Type": "System.Guid",
        "IsRequired": true
      },
      {
        "Name": "request",
        "Type": "EmployeeManagement.Application.DTOs.Request.Role.UpdateRoleRequest",
        "IsRequired": true
      }
    ],
    "ReturnTypes": []
  },
  {
    "ContainingType": "EmployeeManagement.WebAPI.Controllers.RoleController",
    "Method": "Delete",
    "RelativePath": "api/roles/{id}",
    "HttpMethod": "DELETE",
    "IsController": true,
    "Order": 0,
    "Parameters": [
      {
        "Name": "id",
        "Type": "System.Guid",
        "IsRequired": true
      }
    ],
    "ReturnTypes": []
  },
  {
    "ContainingType": "EmployeeManagement.WebAPI.Controllers.RoleController",
    "Method": "AssignPermission",
    "RelativePath": "api/roles/{id}/permissions",
    "HttpMethod": "POST",
    "IsController": true,
    "Order": 0,
    "Parameters": [
      {
        "Name": "id",
        "Type": "System.Guid",
        "IsRequired": true
      },
      {
        "Name": "request",
        "Type": "EmployeeManagement.Application.DTOs.Request.Role.AssignPermissionRequest",
        "IsRequired": true
      }
    ],
    "ReturnTypes": []
  },
  {
    "ContainingType": "EmployeeManagement.WebAPI.Controllers.RoleController",
    "Method": "RemovePermission",
    "RelativePath": "api/roles/{id}/permissions/{permissionId}",
    "HttpMethod": "DELETE",
    "IsController": true,
    "Order": 0,
    "Parameters": [
      {
        "Name": "id",
        "Type": "System.Guid",
        "IsRequired": true
      },
      {
        "Name": "permissionId",
        "Type": "System.Guid",
        "IsRequired": true
      }
    ],
    "ReturnTypes": []
  },
  {
    "ContainingType": "EmployeeManagement.WebAPI.Controllers.SalaryController",
    "Method": "GetByMonthAndYear",
    "RelativePath": "api/salary/{month}/{year}",
    "HttpMethod": "GET",
    "IsController": true,
    "Order": 0,
    "Parameters": [
      {
        "Name": "month",
        "Type": "System.Int32",
        "IsRequired": true
      },
      {
        "Name": "year",
        "Type": "System.Int32",
        "IsRequired": true
      }
    ],
    "ReturnTypes": []
  },
  {
    "ContainingType": "EmployeeManagement.WebAPI.Controllers.SalaryController",
    "Method": "Disburse",
    "RelativePath": "api/salary/disburse",
    "HttpMethod": "POST",
    "IsController": true,
    "Order": 0,
    "Parameters": [
      {
        "Name": "request",
        "Type": "EmployeeManagement.Application.DTOs.Request.Salary.SalaryDisbursementRequest",
        "IsRequired": true
      }
    ],
    "ReturnTypes": []
  },
  {
    "ContainingType": "EmployeeManagement.WebAPI.Controllers.SalaryController",
    "Method": "GetByEmployeeId",
    "RelativePath": "api/salary/history/{employeeId}",
    "HttpMethod": "GET",
    "IsController": true,
    "Order": 0,
    "Parameters": [
      {
        "Name": "employeeId",
        "Type": "System.Guid",
        "IsRequired": true
      }
    ],
    "ReturnTypes": []
  },
  {
    "ContainingType": "EmployeeManagement.WebAPI.Controllers.UserManagementController",
    "Method": "GetAll",
    "RelativePath": "api/users",
    "HttpMethod": "GET",
    "IsController": true,
    "Order": 0,
    "Parameters": [],
    "ReturnTypes": []
  },
  {
    "ContainingType": "EmployeeManagement.WebAPI.Controllers.UserManagementController",
    "Method": "Create",
    "RelativePath": "api/users",
    "HttpMethod": "POST",
    "IsController": true,
    "Order": 0,
    "Parameters": [
      {
        "Name": "request",
        "Type": "EmployeeManagement.Application.DTOs.Request.User.CreateUserRequest",
        "IsRequired": true
      }
    ],
    "ReturnTypes": []
  },
  {
    "ContainingType": "EmployeeManagement.WebAPI.Controllers.UserManagementController",
    "Method": "GetById",
    "RelativePath": "api/users/{id}",
    "HttpMethod": "GET",
    "IsController": true,
    "Order": 0,
    "Parameters": [
      {
        "Name": "id",
        "Type": "System.Guid",
        "IsRequired": true
      }
    ],
    "ReturnTypes": []
  },
  {
    "ContainingType": "EmployeeManagement.WebAPI.Controllers.UserManagementController",
    "Method": "Update",
    "RelativePath": "api/users/{id}",
    "HttpMethod": "PUT",
    "IsController": true,
    "Order": 0,
    "Parameters": [
      {
        "Name": "id",
        "Type": "System.Guid",
        "IsRequired": true
      },
      {
        "Name": "request",
        "Type": "EmployeeManagement.Application.DTOs.Request.User.UpdateUserRequest",
        "IsRequired": true
      }
    ],
    "ReturnTypes": []
  },
  {
    "ContainingType": "EmployeeManagement.WebAPI.Controllers.UserManagementController",
    "Method": "AssignRole",
    "RelativePath": "api/users/{id}/roles",
    "HttpMethod": "POST",
    "IsController": true,
    "Order": 0,
    "Parameters": [
      {
        "Name": "id",
        "Type": "System.Guid",
        "IsRequired": true
      },
      {
        "Name": "request",
        "Type": "EmployeeManagement.Application.DTOs.Request.User.AssignRoleRequest",
        "IsRequired": true
      }
    ],
    "ReturnTypes": []
  },
  {
    "ContainingType": "EmployeeManagement.WebAPI.Controllers.UserManagementController",
    "Method": "RemoveRole",
    "RelativePath": "api/users/{id}/roles/{roleId}",
    "HttpMethod": "DELETE",
    "IsController": true,
    "Order": 0,
    "Parameters": [
      {
        "Name": "id",
        "Type": "System.Guid",
        "IsRequired": true
      },
      {
        "Name": "roleId",
        "Type": "System.Guid",
        "IsRequired": true
      }
    ],
    "ReturnTypes": []
  }
]